otc_backtest/__init__.py
otc_backtest/main.py
otc_backtest/utils.py
otc_backtest/calendar/China/2021.txt
otc_backtest/calendar/China/2022.txt
otc_backtest/calendar/China/2023.txt
otc_backtest/calendar/China/2024.txt
otc_backtest/calendar/China/2025.txt
otc_backtest/calendar/China/2026.txt
otc_backtest/calendar/China/2027.txt
otc_backtest/calendar/China/2028.txt
otc_backtest/data/snowball.csv
otc_backtest-1.0.2.dist-info/METADATA
otc_backtest-1.0.2.dist-info/WHEEL
otc_backtest-1.0.2.dist-info/top_level.txt
otc_backtest-1.0.2.dist-info/RECORD
